rx/providers/hive/__init__.py
rx/providers/hive/hooks/__init__.py
rx/providers/hive/hooks/hive.py
rocketx_providers_hive-0.1.1.dist-info/WHEEL
rocketx_providers_hive-0.1.1.dist-info/METADATA
rocketx_providers_hive-0.1.1.dist-info/RECORD
