Metadata-Version: 2.4
Name: rocketx-providers-hive
Version: 0.1.1
Summary: Add your description here
Author-email: mingminyu <yu_mingm623@163.com>
Requires-Python: >=3.12
Requires-Dist: impyla>=0.21.0
Requires-Dist: loguru>=0.7.3
Requires-Dist: pandas>=2.2.3
Requires-Dist: pytest>=8.3.5
Requires-Dist: sqlparse>=0.5.3
